function_caller/__init__.py
function_caller/assistant.py
function_caller/model_interface.py
function_caller/AI_providers/__init__.py
function_caller/AI_providers/deepinfra.py
function_caller/AI_providers/sambanova.py
function_caller/prompts/__init__.py
function_caller/prompts/default_prompt.py
function_caller/tools/__init__.py
function_caller/tools/sample_tools.py
function_caller/utils/__init__.py
function_caller/utils/history_manager.py
function_caller/utils/logger.py
function_caller/utils/message_formatter.py
function_caller-0.1.2.dist-info/LICENSE
function_caller-0.1.2.dist-info/METADATA
function_caller-0.1.2.dist-info/WHEEL
function_caller-0.1.2.dist-info/top_level.txt
function_caller-0.1.2.dist-info/RECORD
