Metadata-Version: 2.1
Name: function_caller
Version: 0.1.2
Summary: Function calling for AI models without native support.
Home-page: https://github.com/SreejanPersonal/function_caller
Author: Devs Do Code (Sree)
Author-email: devsdocode@gmail.com
Classifier: Programming Language :: Python :: 3
Classifier: License :: OSI Approved :: MIT License
Classifier: Operating System :: OS Independent
Requires-Python: >=3.6
License-File: LICENSE
Requires-Dist: requests
Requires-Dist: colorlog
Requires-Dist: python-dotenv
